chealpix.cpython-311-x86_64-linux-gnu.so
healpix/__init__.py
healpix/test/__init__.py
healpix/test/conftest.py
healpix/test/test_chealpix.py
healpix/test/test_healpix.py
healpix-2025.1.dist-info/METADATA
healpix-2025.1.dist-info/WHEEL
healpix-2025.1.dist-info/top_level.txt
healpix-2025.1.dist-info/RECORD
healpix-2025.1.dist-info/licenses/LICENSE.md
