Metadata-Version: 2.4
Name: healpix
Version: 2025.1
Summary: Python package for HEALPix discretisation of the sphere
Maintainer-email: Nicolas Tessore <n.tessore@ucl.ac.uk>
License: BSD-3-Clause
Project-URL: Homepage, https://github.com/ntessore/healpix
Classifier: Programming Language :: Python :: 3
Classifier: License :: OSI Approved :: BSD License
Classifier: Operating System :: OS Independent
Requires-Python: >=3.9
License-File: LICENSE.md
Requires-Dist: numpy
Provides-Extra: test
Requires-Dist: pytest; extra == "test"
Dynamic: license-file
